textlasso/__init__.py
textlasso/_extractors.py
textlasso/_inprompt_injections.py
textlasso/_parsers.py
textlasso/cleaners.py
textlasso/extract.py
textlasso/prompting.py
textlasso-0.1.3.dist-info/licenses/LICENCE
textlasso-0.1.3.dist-info/METADATA
textlasso-0.1.3.dist-info/WHEEL
textlasso-0.1.3.dist-info/top_level.txt
textlasso-0.1.3.dist-info/RECORD
