Metadata-Version: 2.4
Name: textlasso
Version: 0.1.3
Summary: Simple packege for working with LLM text responses and prompts.
Author-email: Aziz Nadirov <aziznadirov@yahoo.com>
Maintainer-email: Aziz Nadirov <aziznadirov@yahoo.com>
License-Expression: MIT
Project-URL: Homepage, https://github.com/AzizNadirov/textlasso
Project-URL: Repository, https://github.com/AzizNadirov/textlasso.git
Keywords: llm,text,crawl,extract,text-cleaning
Classifier: Development Status :: 4 - Beta
Classifier: Intended Audience :: Developers
Classifier: Programming Language :: Python :: 3
Classifier: Programming Language :: Python :: 3.9
Classifier: Programming Language :: Python :: 3.10
Classifier: Programming Language :: Python :: 3.11
Classifier: Programming Language :: Python :: 3.12
Requires-Python: >=3.9
License-File: LICENCE
Requires-Dist: pandas>=2.3.1
Requires-Dist: xmltodict>=0.14.2
Dynamic: license-file
